{"https://basin-genesis-hub.github.io/Atlas/pages/sample_compression/page.html": {"category": "Compression", "name": "Compression Sample", "url": "https://basin-genesis-hub.github.io/Atlas/pages/sample_compression/page.html", "image": "", "contributor": "rishabh", "tools": {"underworld": true, "citcoms": false, "badlands": false, "other": false, "gplates": false, "pygplates": false, "gmt": false}}, "https://basin-genesis-hub.github.io/Atlas/pages/sample_basin/page.html": {"category": "Basin", "name": "Basin Sample", "url": "https://basin-genesis-hub.github.io/Atlas/pages/sample_basin/page.html", "image": "", "contributor": "danial", "tools": {"underworld": false, "citcoms": false, "badlands": true, "other": false, "gplates": false, "pygplates": false, "gmt": false}}, "https://basin-genesis-hub.github.io/Atlas/pages/sample_fluvio-deltaic/page.html": {"category": "Fluvio-deltaic", "name": "Fluvio-deltaic Sample", "url": "https://basin-genesis-hub.github.io/Atlas/pages/sample_fluvio-deltaic/page.html", "image": "", "contributor": "danial", "tools": {"underworld": false, "citcoms": false, "other": false, "gplates": false, "pygplates": false, "gmt": false, "badlands": true}}, "https://basin-genesis-hub.github.io/Atlas/pages/sample_coupled/page.html": {"category": "Extension-coupled", "name": "Coupled Sample", "url": "https://basin-genesis-hub.github.io/Atlas/pages/sample_coupled/page.html", "image": "", "contributor": "danial", "tools": {"underworld": false, "citcoms": false, "badlands": true, "other": false, "gplates": false, "pygplates": false, "gmt": false}}, "https://basin-genesis-hub.github.io/Atlas/pages/sample_case-studies/page.html": {"category": "Case-studies", "name": "Great Barrier Reef", "url": "https://basin-genesis-hub.github.io/Atlas/pages/sample_case-studies/page.html", "image": "", "contributor": "danial", "tools": {"underworld": false, "citcoms": false, "badlands": false, "other": false, "gplates": false, "pygplates": false, "gmt": false}}, "https://basin-genesis-hub.github.io/Atlas/pages/example/page.html": {"category": "Basin", "name": "Example", "url": "https://basin-genesis-hub.github.io/Atlas/pages/example/page.html", "image": "", "contributor": "danial", "tools": {"underworld": false, "citcoms": false, "badlands": false, "other": false, "gplates": false, "pygplates": false, "gmt": false}}, "https://basin-genesis-hub.github.io/Atlas/pages/sample_uw-strike-slip/page.html": {"category": "Underworld-Strike-slip", "name": "Underworld Strike-slip", "url": "https://basin-genesis-hub.github.io/Atlas/pages/sample_uw-strike-slip/page.html", "image": "", "contributor": "aman", "tools": {"underworld": true, "citcoms": false, "other": false, "gplates": false, "pygplates": false, "gmt": false, "badlands": false}}, "https://basin-genesis-hub.github.io/Atlas/pages/sample_pygplates/page.html": {"category": "PyGplates", "name": "Pygplates Sample", "url": "https://basin-genesis-hub.github.io/Atlas/pages/sample_pygplates/page.html", "image": "", "contributor": "danial", "tools": {"underworld": false, "citcoms": false, "other": false, "gplates": false, "pygplates": true, "gmt": false, "badlands": false}}, "https://basin-genesis-hub.github.io/Atlas/pages/sample_gplates-citcoms/page.html": {"category": "Gplates & Citcoms", "name": "Gplates & Citcoms Sample", "url": "https://basin-genesis-hub.github.io/Atlas/pages/sample_gplates-citcoms/page.html", "image": "", "contributor": "danial", "tools": {"underworld": false, "citcoms": true, "other": false, "gplates": true, "pygplates": false, "gmt": false, "badlands": false}}, "https://basin-genesis-hub.github.io/Atlas/pages/sample_rift/page.html": {"category": "Rift", "name": "Rift Sample", "url": "https://basin-genesis-hub.github.io/Atlas/pages/sample_rift/page.html", "image": "", "contributor": "danial", "tools": {"underworld": false, "citcoms": false, "other": false, "gplates": false, "pygplates": false, "gmt": false, "badlands": true}}, "https://basin-genesis-hub.github.io/Atlas/pages/sample_extension/page.html": {"category": "Extension", "name": "Extension Sample", "url": "https://basin-genesis-hub.github.io/Atlas/pages/sample_extension/page.html", "image": "", "contributor": "aman", "tools": {"underworld": true, "citcoms": false, "other": false, "gplates": false, "pygplates": false, "gmt": false, "badlands": false}}, "https://basin-genesis-hub.github.io/Atlas/pages/sample_bl-strike-slip/page.html": {"category": "Badlands-Strike-slip", "name": "Badlands Strike-slip", "url": "https://basin-genesis-hub.github.io/Atlas/pages/sample_bl-strike-slip/page.html", "image": "", "contributor": "danial", "tools": {"underworld": false, "citcoms": false, "badlands": false, "other": false, "gplates": false, "pygplates": false, "gmt": false}}}